Ronaldo/Domain.py
Ronaldo/Ip.py
Ronaldo/Ronaldo.py
Ronaldo/Util.py
Ronaldo/__init__.py
Ronaldo-0.0.2.dist-info/METADATA
Ronaldo-0.0.2.dist-info/WHEEL
Ronaldo-0.0.2.dist-info/top_level.txt
Ronaldo-0.0.2.dist-info/RECORD
